extra_logging
